textnormalizer/__init__.py
textnormalizer/_exceptions.py
textnormalizer/_metrics.py
textnormalizer/_textnormalizer.py
textnormalizer/_utils.py
t_normalizer-0.0.1.dist-info/LICENSE
t_normalizer-0.0.1.dist-info/METADATA
t_normalizer-0.0.1.dist-info/WHEEL
t_normalizer-0.0.1.dist-info/top_level.txt
t_normalizer-0.0.1.dist-info/RECORD
