Metadata-Version: 2.1
Name: t-normalizer
Version: 0.0.1
Summary: TextNormalizer perform fully supervised text normalization
Home-page: https://github.com/fourat-bs/TextNormalizer
Author: Fourat Ben Salah
Author-email: med.fourat.ben.salah@gmail.com
License: MIT
Platform: UNKNOWN
Requires-Python: >=3.7
License-File: LICENSE
Requires-Dist: numpy (>=1.21.5)
Requires-Dist: torch (>=1.11.0)
Requires-Dist: scikit-learn (>=1.0.2)
Requires-Dist: transformers (>=4.18.0)
Requires-Dist: joblib (>=1.1.0)
